[
  {
    "id": "democratic-iran-war-rhetoric",
    "file": "democratic_iran_war_rhetoric_analysis.md",
    "label": "Democratic Iran War Rhetoric Analysis",
    "type": "analysis",
    "title": "Democratic Leaders' Statements & Claims on the Iran War",
    "word_count": 2680,
    "section_count": 27,
    "quote_count": 21,
    "table_line_count": 37,
    "themes": [
      "legality-and-war-powers",
      "diplomacy",
      "imminence-and-threat",
      "public-opinion"
    ],
    "actors": [
      "bernie-sanders",
      "elizabeth-warren",
      "ed-markey",
      "ro-khanna",
      "adam-schiff",
      "tim-kaine",
      "mark-warner",
      "hakeem-jeffries",
      "chuck-schumer",
      "chris-murphy",
      "richard-blumenthal",
      "angus-king",
      "ruben-gallego",
      "alexandria-ocasio-cortez",
      "rashida-tlaib",
      "cory-booker",
      "nancy-pelosi",
      "andy-kim",
      "john-fetterman",
      "josh-gottheimer",
      "jared-moskowitz",
      "jimmy-panetta",
      "henry-cuellar",
      "greg-landsman",
      "jared-golden",
      "jim-costa",
      "donald-trump",
      "marco-rubio",
      "benjamin-netanyahu",
      "ali-khamenei",
      "thomas-massie",
      "rand-paul"
    ],
    "dates": [
      "Feb 24, 2026",
      "Feb 25, 2026",
      "Feb 28, 2026",
      "Jan 29, 2026",
      "Mar 1, 2026",
      "Mar 3, 2026",
      "Mar 4, 2026",
      "March 5, 2026"
    ]
  },
  {
    "id": "democrat-fiscal-irony",
    "file": "democrat_fiscal_irony_iran.md",
    "label": "Fiscal Irony Analysis",
    "type": "analysis",
    "title": "\"Wasting Taxpayer Money on Iran\": A Critique of the Democratic Fiscal Argument",
    "word_count": 2206,
    "section_count": 19,
    "quote_count": 0,
    "table_line_count": 54,
    "themes": [
      "domestic-priorities",
      "fiscal-irony",
      "diplomacy",
      "historical-comparisons"
    ],
    "actors": [
      "bernie-sanders",
      "tim-kaine",
      "hakeem-jeffries",
      "chris-murphy",
      "angus-king",
      "cory-booker",
      "donald-trump"
    ],
    "dates": [
      "March 5, 2026"
    ]
  },
  {
    "id": "democratic-moral-irony",
    "file": "democratic_moral_irony_analysis.md",
    "label": "Moral Irony Analysis",
    "type": "analysis",
    "title": "The Moral Arithmetic: Democratic Rhetoric on Soldier Deaths vs. Deaths Enabled by Democratic Policies",
    "word_count": 2349,
    "section_count": 22,
    "quote_count": 0,
    "table_line_count": 29,
    "themes": [
      "moral-irony",
      "narcotics-networks",
      "domestic-priorities",
      "imminence-and-threat"
    ],
    "actors": [
      "bernie-sanders",
      "elizabeth-warren",
      "tim-kaine",
      "chris-murphy",
      "angus-king",
      "ruben-gallego",
      "donald-trump"
    ],
    "dates": [
      "March 5, 2026"
    ]
  },
  {
    "id": "iran-vs-iraq-afghanistan",
    "file": "iran_vs_iraq_afghanistan_comparison.md",
    "label": "Iran vs Iraq Afghanistan Comparison",
    "type": "comparison",
    "title": "Why Iran 2026 Is Not Iraq 2003 or Afghanistan 2001",
    "word_count": 2601,
    "section_count": 14,
    "quote_count": 1,
    "table_line_count": 27,
    "themes": [
      "historical-comparisons",
      "nuclear-program",
      "legality-and-war-powers",
      "proxy-violence"
    ],
    "actors": [
      "bernie-sanders",
      "mark-warner",
      "chuck-schumer",
      "angus-king",
      "andy-kim",
      "donald-trump"
    ],
    "dates": [
      "March 5, 2026"
    ]
  },
  {
    "id": "jeffries-deep-dive",
    "file": "jeffries_iran_statements_deep_dive.md",
    "label": "Jeffries Statements Deep Dive",
    "type": "profile",
    "title": "Hakeem Jeffries: Complete Public Statements on Iran",
    "word_count": 3006,
    "section_count": 21,
    "quote_count": 68,
    "table_line_count": 25,
    "themes": [
      "legality-and-war-powers",
      "imminence-and-threat",
      "historical-comparisons",
      "jeffries-evolution"
    ],
    "actors": [
      "ro-khanna",
      "mark-warner",
      "hakeem-jeffries",
      "chuck-schumer",
      "angus-king",
      "ruben-gallego",
      "rashida-tlaib",
      "john-fetterman",
      "donald-trump",
      "ali-khamenei",
      "thomas-massie"
    ],
    "dates": [
      "Feb 24, 2026",
      "Feb 28, 2026",
      "February 24, 2026",
      "February 28, 2026",
      "January 10, 2026",
      "June 19, 2025",
      "June 20, 2025",
      "June 23, 2025",
      "March 1, 2026",
      "March 3, 2026"
    ]
  },
  {
    "id": "omissions-analysis",
    "file": "democrat_iran_omissions_analysis.md",
    "label": "Omissions Analysis",
    "type": "counter-narrative",
    "title": "What Democrats & Liberal Politicians Are Downplaying, Omitting, or Refusing to Acknowledge on Iran",
    "word_count": 2695,
    "section_count": 16,
    "quote_count": 2,
    "table_line_count": 12,
    "themes": [
      "cyber-threats",
      "human-rights",
      "nuclear-program",
      "proxy-violence"
    ],
    "actors": [
      "bernie-sanders",
      "elizabeth-warren",
      "hakeem-jeffries",
      "chris-murphy",
      "angus-king",
      "donald-trump",
      "marco-rubio"
    ],
    "dates": [
      "February 20, 2026",
      "February 27, 2026",
      "Jan 28, 2024",
      "January 10, 2026",
      "June 12, 2025",
      "June 25, 2025",
      "June 9, 2025",
      "March 4, 2026",
      "March 5, 2026",
      "October 7, 2024"
    ]
  },
  {
    "id": "omissions-expanded",
    "file": "democrat_iran_omissions_expanded.md",
    "label": "Expanded Omissions Analysis",
    "type": "counter-narrative",
    "title": "What Democrats & Liberal Politicians Are Downplaying, Omitting, or Refusing to Acknowledge on Iran",
    "word_count": 3699,
    "section_count": 17,
    "quote_count": 2,
    "table_line_count": 16,
    "themes": [
      "cyber-threats",
      "human-rights",
      "nuclear-program",
      "proxy-violence"
    ],
    "actors": [
      "bernie-sanders",
      "elizabeth-warren",
      "hakeem-jeffries",
      "chuck-schumer",
      "chris-murphy",
      "angus-king",
      "josh-gottheimer",
      "jimmy-panetta",
      "henry-cuellar",
      "greg-landsman",
      "jared-golden",
      "jim-costa",
      "donald-trump",
      "marco-rubio",
      "ali-khamenei"
    ],
    "dates": [
      "February 20, 2026",
      "February 27, 2026",
      "Jan 28, 2024",
      "January 10, 2026",
      "June 12, 2025",
      "June 25, 2025",
      "June 9, 2025",
      "March 2, 2026",
      "March 4, 2026",
      "March 5, 2026"
    ]
  },
  {
    "id": "democratic-iran-war-statements-docx",
    "file": "Democratic-Iran-War-Statements_extracted.md",
    "label": "Democratic Iran War Statements Document",
    "type": "compiled-report",
    "title": "Democratic Leaders' Statements & Claims on the Iran War",
    "word_count": 4786,
    "section_count": 1,
    "quote_count": 0,
    "table_line_count": 42,
    "themes": [
      "legality-and-war-powers",
      "diplomacy",
      "imminence-and-threat",
      "public-opinion"
    ],
    "actors": [
      "bernie-sanders",
      "elizabeth-warren",
      "ed-markey",
      "ro-khanna",
      "adam-schiff",
      "tim-kaine",
      "mark-warner",
      "hakeem-jeffries",
      "chuck-schumer",
      "chris-murphy",
      "richard-blumenthal",
      "angus-king",
      "ruben-gallego",
      "alexandria-ocasio-cortez",
      "rashida-tlaib",
      "cory-booker",
      "andy-kim",
      "john-fetterman",
      "josh-gottheimer",
      "jared-moskowitz",
      "jimmy-panetta",
      "henry-cuellar",
      "greg-landsman",
      "jared-golden",
      "jim-costa",
      "donald-trump",
      "marco-rubio",
      "benjamin-netanyahu",
      "ali-khamenei",
      "thomas-massie",
      "rand-paul"
    ],
    "dates": [
      "Feb 24, 2026",
      "Feb 25, 2026",
      "Feb 28, 2026",
      "February 28, 2026",
      "Jan 29, 2026",
      "Mar 1, 2026",
      "Mar 4, 2026",
      "March 1, 2026",
      "March 3, 2026",
      "March 4, 2026"
    ]
  },
  {
    "id": "research-brief-docx",
    "file": "I-need-to-conduct-a-deep-investigation-and-analysi_extracted.md",
    "label": "Research Brief and Expansion Trail",
    "type": "brief",
    "title": "Eight Core Democratic Arguments",
    "word_count": 17768,
    "section_count": 1,
    "quote_count": 0,
    "table_line_count": 18,
    "themes": [
      "human-rights",
      "fiscal-irony",
      "imminence-and-threat",
      "legality-and-war-powers"
    ],
    "actors": [
      "bernie-sanders",
      "elizabeth-warren",
      "ed-markey",
      "ro-khanna",
      "adam-schiff",
      "tim-kaine",
      "mark-warner",
      "hakeem-jeffries",
      "chuck-schumer",
      "chris-murphy",
      "richard-blumenthal",
      "angus-king",
      "ruben-gallego",
      "alexandria-ocasio-cortez",
      "rashida-tlaib",
      "cory-booker",
      "nancy-pelosi",
      "john-fetterman",
      "josh-gottheimer",
      "jimmy-panetta",
      "henry-cuellar",
      "greg-landsman",
      "jared-golden",
      "jim-costa",
      "donald-trump",
      "marco-rubio",
      "benjamin-netanyahu",
      "ali-khamenei",
      "rand-paul"
    ],
    "dates": [
      "June 9, 2025",
      "March 2, 2026",
      "March 4, 2026"
    ]
  }
]
